blogtuner/__init__.py
blogtuner/__main__.py
blogtuner/ai/llm.py
blogtuner/cli/__init__.py
blogtuner/cli/core.py
blogtuner/cli/importer.py
blogtuner/cli/post.py
blogtuner/core/blog.py
blogtuner/core/post.py
blogtuner/core/site.py
blogtuner/data/l10n/ca/LC_MESSAGES/messages.mo
blogtuner/data/l10n/ca/LC_MESSAGES/messages.po
blogtuner/data/l10n/messages.pot
blogtuner/data/statics/bundle.css
blogtuner/data/templates/base.html.jinja
blogtuner/data/templates/list.html.jinja
blogtuner/data/templates/post.html.jinja
blogtuner/importers/substack.py
blogtuner/rendering/markdown.py
blogtuner/rendering/site.py
blogtuner/rendering/templates.py
blogtuner/utils/date.py
blogtuner/utils/git.py
blogtuner/utils/images.py
blogtuner/utils/logs.py
blogtuner/utils/paths.py
blogtuner-0.13.8.dist-info/licenses/LICENSE
blogtuner-0.13.8.dist-info/WHEEL
blogtuner-0.13.8.dist-info/entry_points.txt
blogtuner-0.13.8.dist-info/METADATA
blogtuner-0.13.8.dist-info/RECORD
