Metadata-Version: 2.4
Name: blogtuner
Version: 0.13.8
Summary: Dead simple static blog generator using markdown files
Author: All Tuner Labs
Author-email: All Tuner Labs <hey@alltuner.com>
License-Expression: MIT
License-File: LICENSE
Classifier: Development Status :: 4 - Beta
Classifier: Environment :: Console
Classifier: Framework :: Pydantic
Classifier: Framework :: Pydantic :: 2
Classifier: Intended Audience :: Developers
Classifier: Intended Audience :: End Users/Desktop
Classifier: Intended Audience :: Information Technology
Classifier: License :: OSI Approved :: MIT License
Classifier: Operating System :: OS Independent
Classifier: Programming Language :: Python :: 3 :: Only
Classifier: Programming Language :: Python :: 3
Classifier: Programming Language :: Python :: 3.12
Classifier: Programming Language :: Python :: 3.13
Classifier: Programming Language :: Python :: 3.14
Classifier: Topic :: Internet :: WWW/HTTP :: Site Management
Classifier: Topic :: Text Processing :: Markup :: HTML
Classifier: Topic :: Text Processing :: Markup :: Markdown
Classifier: Topic :: Utilities
Classifier: Typing :: Typed
Requires-Dist: babel>=2.17.0
Requires-Dist: click>=8.3.1
Requires-Dist: feedgen>=1.0.0
Requires-Dist: gitpython>=3.1.45
Requires-Dist: jinja2>=3.1.6
Requires-Dist: llm>=0.27.1
Requires-Dist: loguru>=0.7.3
Requires-Dist: mdformat>=1.0.0
Requires-Dist: mistune>=3.1.4
Requires-Dist: pillow>=12.0.0
Requires-Dist: pydantic>=2.12.5
Requires-Dist: pygments>=2.19.2
Requires-Dist: python-dateutil>=2.9.0.post0
Requires-Dist: python-dotenv>=1.2.1
Requires-Dist: python-frontmatter>=1.1.0
Requires-Dist: python-slugify[unidecode]>=8.0.4
Requires-Dist: requests>=2.32.5
Requires-Dist: substack-api>=1.1.3
Requires-Dist: toml>=0.10.2
Requires-Dist: typer>=0.20.0
Requires-Dist: types-jinja2>=2.11.9
Requires-Python: >=3.12
Project-URL: Homepage, https://github.com/alltuner/blogtuner
Project-URL: Issues, https://github.com/alltuner/blogtuner/issues
